zfsexporter/__init__.py
zfsexporter/zfsexporter.py
zfsexporter_tspspi-0.0.2.dist-info/LICENSE.md
zfsexporter_tspspi-0.0.2.dist-info/METADATA
zfsexporter_tspspi-0.0.2.dist-info/WHEEL
zfsexporter_tspspi-0.0.2.dist-info/entry_points.txt
zfsexporter_tspspi-0.0.2.dist-info/top_level.txt
zfsexporter_tspspi-0.0.2.dist-info/RECORD
