Metadata-Version: 2.1
Name: zfsexporter-tspspi
Version: 0.0.2
Summary: Simple exporter for Prometheus that supplies ZFS filesystem and zpool information
Home-page: https://github.com/tspspi/zfsexporter
Author: Thomas Spielauer
Author-email: pypipackages01@tspi.at
License: UNKNOWN
Platform: UNKNOWN
Classifier: Programming Language :: Python :: 3
Classifier: License :: OSI Approved :: BSD License
Classifier: Operating System :: POSIX :: BSD :: FreeBSD
Requires-Python: >=3.6
License-File: LICENSE.md
Requires-Dist: daemonize (>=2.5.0)
Requires-Dist: lockfile (>=0.12.2)
Requires-Dist: prometheus-client (>=0.13.1)
